{
  "paintings": [
    {
      "title": "Aah Critter",
      "date": "2023-05-21T11:00:00.000Z",
      "summary": "Aah Critter: a painting by David Rhoden",
      "image": "/static/img/paintings/aah-critter-on-shed-may-21-2023.png",
      "height": 40,
      "width": 24,
      "price": 210,
      "forsale": true,
      "material": "enamel on plywood",
      "tags": ["paintings"]
    },
    {
      "title": "Aah Guy",
      "date": "2023-05-27T11:00:00.000Z",
      "summary": "Aah Guy: a painting by David Rhoden",
      "image": "/static/img/paintings/aah-guy-on-shed-may-27-2023.png",
      "height": 40,
      "width": 40,
      "price": 210,
      "forsale": true,
      "material": "enamel on plywood",
      "tags": ["paintings"]
    },
    {
      "title": "Amputee",
      "date": "2023-05-20T00:00:00.000Z",
      "summary": "Amputee: a painting by David Rhoden",
      "image": "/static/img/paintings/amputee-reclaimed-mar-17-2025.jpg",
      "height": null,
      "width": null,
      "price": 360,
      "forsale": true,
      "material": "enamel on plywood",
      "tags": ["paintings"]
    },
    {
      "title": "Babbler",
      "date": "2006-04-04T00:00:00.000Z",
      "summary": "Babbler: a painting by David Rhoden",
      "image": "/static/img/paintings/babbler-apr-4-2006.jpg",
      "height": null,
      "width": null,
      "price": "SOLD",
      "forsale": false,
      "material": "enamel on plywood",
      "tags": ["paintings"]
    },
    {
      "title": "Betty",
      "date": "2025-12-20T11:00:00.000Z",
      "summary": "Betty: a painting by David Rhoden",
      "image": "/static/img/paintings/betty-1000.jpg",
      "height": null,
      "width": null,
      "price": "SOLD",
      "forsale": false,
      "material": "enamel on plywood",
      "tags": ["paintings", "cats"]
    },
    {
      "title": "Blobby (standing)",
      "date": "2025-01-01T00:00:00",
      "summary": "Blobby (standing): a painting by David Rhoden",
      "image": "/static/img/paintings/blobby-standing.png",
      "height": 31,
      "width": 22,
      "price": 120,
      "forsale": true,
      "material": "enamel on plywood",
      "tags": ["paintings"]
    },
    {
      "title": "Blue Squiggle",
      "date": "2017-08-20T00:00:00",
      "summary": "Blue Squiggle: a painting by David Rhoden",
      "image": "/static/img/paintings/blue-squiggle-aug-20-2017.png",
      "height": null,
      "width": null,
      "price": "SOLD",
      "forsale": false,
      "material": "enamel on plywood",
      "tags": ["paintings", "squiggles", "2017"]
    },
    {
      "title": "Bottlecap",
      "date": "2021-02-02T00:00:00",
      "summary": "Bottlecap: a painting by David Rhoden",
      "image": "/static/img/paintings/bottlecap.jpg",
      "height": null,
      "width": null,
      "price": "SOLD",
      "forsale": false,
      "material": "enamel on plywood",
      "tags": ["paintings"]
    },
    {
      "title": "Chap",
      "date": "2026-01-04T00:00:00.000Z",
      "summary": "Chap: a painting by David Rhoden",
      "image": "/static/img/paintings/chap-jan-4-2026.jpg",
      "height": 32,
      "width": 23,
      "price": 120,
      "forsale": true,
      "material": "enamel on plywood",
      "tags": ["paintings"]
    },
    {
      "title": "Charter",
      "date": "2023-05-20T00:00:00.000Z",
      "summary": "Charter: a painting by David Rhoden",
      "image": "/static/img/paintings/bus-sep-24-2019.jpg",
      "height": 45,
      "width": 31,
      "price": "SOLD",
      "forsale": false,
      "material": "enamel on plywood",
      "tags": ["paintings"]
    },
    {
      "title": "Cloud Creatures",
      "date": "2025-12-22T00:00:00.000Z",
      "summary": "Cloud Creatures: a painting by David Rhoden",
      "image": "/static/img/paintings/cloud-creatures.jpg",
      "height": null,
      "width": null,
      "price": "SOLD",
      "forsale": false,
      "material": "enamel on plywood",
      "tags": ["paintings"]
    },
    {
      "title": "Cloud Mouths",
      "date": "2025-12-28T00:00:00",
      "summary": "Cloud Mouths: a painting by David Rhoden",
      "image": "/static/img/paintings/cloudmouths.jpg",
      "height": null,
      "width": null,
      "price": "SOLD",
      "forsale": false,
      "material": "oil, chalk pastel on canvas",
      "tags": ["paintings", "canvas"]
    },
    {
      "title": "Conventionality Belongs To Yesterday",
      "date": "2023-10-15T11:00:00.000Z",
      "summary": "Conventionality Belongs To Yesterday: a painting by David Rhoden",
      "image": "/static/img/paintings/conventionality-oct-2023.jpg",
      "height": 24,
      "width": 16,
      "price": 210,
      "forsale": true,
      "material": "enamel on plywood",
      "tags": ["paintings"]
    },
    {
      "title": "Daddy Long Legs",
      "date": "2023-05-20T00:00:00.000Z",
      "summary": "Daddy Long Legs: a painting by David Rhoden",
      "image": "/static/img/paintings/sized_exports/daddy-long-legs.png",
      "height": 32,
      "width": 36,
      "price": "SOLD",
      "forsale": false,
      "material": "enamel on plywood",
      "tags": ["paintings"]
    },
    {
      "title": "Dominante",
      "date": "2023-05-20T00:00:00.000Z",
      "summary": "Dominante: a painting by David Rhoden",
      "image": "/static/img/paintings/dominante-outside.png",
      "height": 78,
      "width": 23,
      "price": 450,
      "forsale": true,
      "material": "enamel on plywood",
      "tags": ["paintings"]
    },
    {
      "title": "Dotted Eye",
      "date": "2023-05-20T00:00:00.000Z",
      "summary": "Dotted Eye: a painting by David Rhoden",
      "image": "/static/img/paintings/blackeye-reclaimed-mar-17-2025.jpg",
      "height": null,
      "width": null,
      "price": 360,
      "forsale": true,
      "material": "enamel on plywood",
      "tags": ["paintings"]
    },
    {
      "title": "Eater",
      "date": "2023-05-20T00:00:00.000Z",
      "summary": "Eater: a painting by David Rhoden",
      "image": "/static/img/paintings/eater.jpg",
      "height": 24,
      "width": 37,
      "price": 150,
      "forsale": true,
      "material": "enamel on plywood",
      "tags": ["paintings"]
    },
    {
      "title": "Forest Wizard",
      "date": "2024-10-19T00:00:00",
      "summary": "Forest Wizard: a painting by David Rhoden",
      "image": "/static/img/paintings/forest-wizard-oct-19-2024.jpg",
      "height": null,
      "width": null,
      "price": "SOLD",
      "forsale": false,
      "material": "enamel on plywood",
      "tags": ["paintings", "wizards"]
    },
    {
      "title": "Forklift",
      "date": "2023-11-19T00:00:00.000Z",
      "summary": "Forklift: a painting by David Rhoden",
      "image": "/static/img/paintings/forklift-nov-19-2023.jpg",
      "height": 30,
      "width": 40,
      "price": 360,
      "forsale": true,
      "material": "enamel on plywood",
      "tags": ["paintings"]
    },
    {
      "title": "Friendly Woman In Workout Clothes",
      "date": "2025-04-09T00:00:00.000Z",
      "summary": "Friendly Woman In Workout Clothes: a painting by David Rhoden",
      "image": "/static/img/paintings/workout-clothes-apr-9-2025.jpg",
      "height": 36,
      "width": 16,
      "price": 240,
      "forsale": true,
      "material": "enamel on plywood",
      "tags": ["paintings"]
    },
    {
      "title": "El Fuego Misterioso",
      "date": "2013-11-09T00:00:00.000Z",
      "summary": "Chap: a painting by David Rhoden",
      "image": "/static/img/paintings/el-fuego-misterioso-nov-9-2013.jpg",
      "height": null,
      "width": null,
      "price": "SOLD",
      "forsale": false,
      "material": "enamel on plywood",
      "tags": ["paintings"]
    },
    {
      "title": "Give Me Your Money",
      "date": "2023-05-16T00:00:00.000Z",
      "summary": "wow it's great",
      "image": "/static/img/paintings/give-me-your-money.jpg",
      "height": 73,
      "width": 20,
      "price": 450,
      "forsale": true,
      "material": "enamel on plywood",
      "tags": ["paintings"]
    },
    {
      "title": "I'm Holding In A Lot Of Anger",
      "date": "2006-04-04T00:00:00.000Z",
      "summary": "I'm Holding In A Lot Of Anger: a painting by David Rhoden",
      "image": "/static/img/paintings/holding-anger-on-tx-wall-may-15-2016.png",
      "height": null,
      "width": null,
      "price": "SOLD",
      "forsale": false,
      "material": "enamel on plywood",
      "tags": ["paintings"]
    },
    {
      "title": "A Face",
      "date": "2025-12-20T00:00:00.000Z",
      "summary": "A Face: a painting by David Rhoden",
      "image": "/static/img/paintings/just-a-face.png",
      "height": 17,
      "width": 14,
      "price": 90,
      "forsale": true,
      "material": "enamel on plywood",
      "tags": ["paintings"]
    },
    {
      "title": "Keys",
      "date": "2023-05-20T00:00:00.000Z",
      "summary": "Keys: a painting by David Rhoden",
      "image": "/static/img/paintings/keys.jpg",
      "height": 24,
      "width": 38,
      "price": "SOLD",
      "forsale": false,
      "material": "enamel on plywood",
      "tags": ["paintings"]
    },
    {
      "title": "Kiss Guy",
      "date": "2023-05-20T00:00:00.000Z",
      "summary": "Kiss Guy: a painting by David Rhoden",
      "image": "/static/img/paintings/kiss-guy.jpg",
      "height": 47,
      "width": 22,
      "price": "NFS",
      "forsale": false,
      "material": "enamel on plywood",
      "tags": ["paintings"]
    },
    {
      "title": "Lighter",
      "date": "2023-05-20T00:00:00.000Z",
      "summary": "Lighter: a painting by David Rhoden",
      "image": "/static/img/paintings/lighter-jul-19-2020.jpg",
      "height": 34,
      "width": 16,
      "price": 150,
      "forsale": true,
      "material": "enamel on plywood",
      "tags": ["paintings"]
    },
    {
      "title": "Many-Eyed Monster 2",
      "date": "2023-05-20T00:00:00.000Z",
      "summary": "Many-Eyed Monster 2: a painting by David Rhoden",
      "image": "/static/img/paintings/many-eyed-monster-2.jpg",
      "height": 19,
      "width": 16,
      "price": "SOLD",
      "forsale": false,
      "material": "enamel on plywood",
      "tags": ["paintings"]
    },
    {
      "title": "Orange Squiggle",
      "date": "2014-04-06T00:00:00",
      "summary": "Orange Squiggle: a painting by David Rhoden",
      "image": "/static/img/paintings/orange-squiggle-sold-apr-6-2014.jpg",
      "height": null,
      "width": null,
      "price": "SOLD",
      "forsale": false,
      "material": "enamel on plywood",
      "tags": ["paintings", "squiggles", "2014"]
    },
    {
      "title": "Organic Form (Chrome Yellow)",
      "date": "2023-05-20T00:00:00.000Z",
      "summary": "Organic Form (Orange): a painting by David Rhoden",
      "image": "/static/img/paintings/organic-form-chrome-yellow.jpg",
      "height": 39,
      "width": 33,
      "price": 360,
      "forsale": true,
      "material": "enamel on plywood",
      "tags": ["paintings"]
    },
    {
      "title": "Organic Form (Dark Purple)",
      "date": "2023-05-20T00:00:00.000Z",
      "summary": "Organic Form (Dark Purple): a painting by David Rhoden",
      "image": "/static/img/paintings/organic-form-dark-purple-on-shed.png",
      "height": 52,
      "width": 48,
      "price": 420,
      "forsale": true,
      "material": "enamel on plywood",
      "tags": ["paintings"]
    },
    {
      "title": "Organic Form (Fluorescent Yellow)",
      "date": "2023-05-20T00:00:00.000Z",
      "summary": "Organic Form (Fluorescent Yellow): a painting by David Rhoden",
      "image": "/static/img/paintings/organic-form-fluoro-yellow.png",
      "height": 36,
      "width": 31,
      "price": 300,
      "forsale": true,
      "material": "enamel on plywood",
      "tags": ["paintings"]
    },
    {
      "title": "Organic Form (Magenta)",
      "date": "2021-01-17T00:00:00",
      "summary": "Organic Form (Magenta): a painting by David Rhoden",
      "image": "/static/img/paintings/organic-form-magenta-jan-17-2021.jpg",
      "height": null,
      "width": null,
      "price": "SOLD",
      "forsale": false,
      "material": "enamel on plywood",
      "tags": ["paintings", "organic form", "2021"]
    },
    {
      "title": "Organic Form (Small Purple)",
      "date": "2025-03-30T00:00:00.000Z",
      "summary": "Organic Form (Small Purple): a painting by David Rhoden",
      "image": "/static/img/paintings/organic-form-purple-march-30-2025.png",
      "height": 25,
      "width": 23,
      "price": 210,
      "forsale": true,
      "material": "enamel on plywood",
      "tags": ["paintings"]
    },
    {
      "title": "I Was Talking To Peachy Peach",
      "date": "2025-07-04T00:00:00.000Z",
      "summary": "I Was Talking To Peachy Peach: a painting by David Rhoden",
      "image": "/static/img/paintings/peachy-peach-kissy-kiss.jpg",
      "height": 12,
      "width": 18,
      "price": 120,
      "forsale": true,
      "material": "enamel on plywood. metal rod, shoestring",
      "tags": ["paintings"]
    },
    {
      "title": "Pink Face",
      "date": "2023-05-20T00:00:00.000Z",
      "summary": "Pink Face: a painting by David Rhoden",
      "image": "/static/img/paintings/pink-face.jpg",
      "height": 19,
      "width": 26,
      "price": "SOLD",
      "forsale": false,
      "material": "enamel on plywood",
      "tags": ["paintings"]
    },
    {
      "title": "Pipes",
      "date": "2016-11-10T00:00:00",
      "summary": "Pipes: a painting by David Rhoden",
      "image": "/static/img/paintings/pipes-on-wall-may-12-2016.png",
      "height": null,
      "width": null,
      "price": "SOLD",
      "forsale": false,
      "material": "enamel on plywood",
      "tags": ["paintings"]
    },
    {
      "title": "Rings",
      "date": "2023-05-20T00:00:00.000Z",
      "summary": "Rings: a painting by David Rhoden",
      "image": "/static/img/paintings/sized_exports/rings.png",
      "height": 52,
      "width": 44,
      "price": 300,
      "forsale": true,
      "material": "enamel on plywood",
      "tags": []
    },
    {
      "title": "Snowmobile",
      "date": "2023-05-20T00:00:00.000Z",
      "summary": "Snowmobile: a painting by David Rhoden",
      "image": "/static/img/paintings/snowmobile.jpg",
      "height": 45,
      "width": 31,
      "price": 210,
      "forsale": true,
      "material": "enamel on plywood",
      "tags": ["paintings"]
    },
    {
      "title": "Startlebot",
      "date": "2023-05-20T00:00:00.000Z",
      "summary": "Startlebot: a painting by David Rhoden",
      "image": "/static/img/paintings/startlebot.jpg",
      "height": 20,
      "width": 32,
      "price": 120,
      "forsale": true,
      "material": "enamel on plywood",
      "tags": ["paintings"]
    },
    {
      "title": "Stop Laughing",
      "date": "2026-02-19T11:00:00.000Z",
      "summary": "Stop Laughing: a painting by David Rhoden",
      "image": "/static/img/paintings/stop-laughing-painting-final-feb-19-2026.jpg",
      "height": 22,
      "width": 18,
      "price": 150,
      "forsale": true,
      "material": "enamel on plywood",
      "tags": ["paintings", "Stop Laughing"]
    },
    {
      "title": "Stumpgrinder",
      "date": "2021-02-02T00:00:00",
      "summary": "Stumpgrinder: a painting by David Rhoden",
      "image": "/static/img/paintings/rayco-stumpgrinder-feb-2-2021.jpg",
      "height": null,
      "width": null,
      "price": "SOLD",
      "forsale": false,
      "material": "enamel on plywood",
      "tags": ["paintings"]
    },
    {
      "title": "Arm Scratcher",
      "date": "2013-01-01T00:00:00.000Z",
      "summary": "Arm Scratcher: a painting by David Rhoden",
      "image": "/static/img/paintings/arm-scratcher-now-lost-2013.jpg",
      "height": null,
      "width": null,
      "price": "LOST",
      "forsale": false,
      "material": "enamel on plywood",
      "tags": ["paintings"]
    },
    {
      "title": "Avatar",
      "date": "2011-08-06T00:00:00.000Z",
      "summary": "Avatar: a painting by David Rhoden",
      "image": "/static/img/paintings/avatar-by-amber-aug-6-2011.jpg",
      "height": null,
      "width": null,
      "price": null,
      "forsale": true,
      "material": "enamel on plywood",
      "tags": ["paintings"]
    },
    {
      "title": "Awful Baby",
      "date": "2023-01-01T00:00:00.000Z",
      "summary": "Awful Baby: a painting by David Rhoden",
      "image": "/static/img/paintings/awfulbaby1.jpg",
      "height": null,
      "width": null,
      "price": null,
      "forsale": true,
      "material": "enamel on plywood",
      "tags": ["paintings"]
    },
    {
      "title": "Big Head",
      "date": "2023-01-01T00:00:00.000Z",
      "summary": "Big Head: a painting by David Rhoden",
      "image": "/static/img/paintings/big-head.jpg",
      "height": null,
      "width": null,
      "price": null,
      "forsale": true,
      "material": "enamel on plywood",
      "tags": ["paintings"]
    },
    {
      "title": "Blobman",
      "date": "2023-01-01T00:00:00.000Z",
      "summary": "Blobman: a painting by David Rhoden",
      "image": "/static/img/paintings/blobman.jpg",
      "height": null,
      "width": null,
      "price": null,
      "forsale": true,
      "material": "enamel on plywood",
      "tags": ["paintings"]
    },
    {
      "title": "Blue Lucha",
      "date": "2016-11-06T00:00:00.000Z",
      "summary": "Blue Lucha: a painting by David Rhoden",
      "image": "/static/img/paintings/blue-lucha-nov-6-2016.png",
      "height": null,
      "width": null,
      "price": null,
      "forsale": true,
      "material": "enamel on plywood",
      "tags": ["paintings"]
    },
    {
      "title": "Blue Many Teeth",
      "date": "2023-01-01T00:00:00.000Z",
      "summary": "Blue Many Teeth: a painting by David Rhoden",
      "image": "/static/img/paintings/painting-blue-many-teeth.jpg",
      "height": null,
      "width": null,
      "price": null,
      "forsale": true,
      "material": "enamel on plywood",
      "tags": ["paintings"]
    },
    {
      "title": "Breathers",
      "date": "2023-01-01T00:00:00.000Z",
      "summary": "Breathers: a painting by David Rhoden",
      "image": "/static/img/paintings/breathers-canvas.jpeg",
      "height": null,
      "width": null,
      "price": null,
      "forsale": true,
      "material": "oil, chalk pastel on canvas",
      "tags": ["paintings", "canvas"]
    },
    {
      "title": "Cartoony Face",
      "date": "2023-01-01T00:00:00.000Z",
      "summary": "Cartoony Face: a painting by David Rhoden",
      "image": "/static/img/paintings/cartoony-face.jpg",
      "height": null,
      "width": null,
      "price": null,
      "forsale": true,
      "material": "enamel on plywood",
      "tags": ["paintings"]
    },
    {
      "title": "Corn on the Cob",
      "date": "2023-01-01T00:00:00.000Z",
      "summary": "Corn on the Cob: a painting by David Rhoden",
      "image": "/static/img/paintings/corn-on-the-cob.jpg",
      "height": null,
      "width": null,
      "price": null,
      "forsale": true,
      "material": "enamel on plywood",
      "tags": ["paintings"]
    },
    {
      "title": "Crop Failure 2038",
      "date": "2025-10-30T00:00:00.000Z",
      "summary": "Crop Failure 2038: a painting by David Rhoden",
      "image": "/static/img/paintings/crop-failure-2038-porch-oct-30-2025.jpeg",
      "height": null,
      "width": null,
      "price": null,
      "forsale": true,
      "material": "enamel on plywood",
      "tags": ["paintings"]
    },
    {
      "title": "Dottage",
      "date": "2023-01-01T00:00:00.000Z",
      "summary": "Dottage: a painting by David Rhoden",
      "image": "/static/img/paintings/dottage.jpg",
      "height": null,
      "width": null,
      "price": null,
      "forsale": true,
      "material": "enamel on plywood",
      "tags": ["paintings"]
    },
    {
      "title": "Face Like a Thumb",
      "date": "2023-01-01T00:00:00.000Z",
      "summary": "Face Like a Thumb: a painting by David Rhoden",
      "image": "/static/img/paintings/facelikeathumb.jpg",
      "height": null,
      "width": null,
      "price": null,
      "forsale": true,
      "material": "enamel on plywood",
      "tags": ["paintings"]
    },
    {
      "title": "Figure Study",
      "date": "2023-01-01T00:00:00.000Z",
      "summary": "Figure Study: a painting by David Rhoden",
      "image": "/static/img/paintings/figurestudy.jpg",
      "height": null,
      "width": null,
      "price": null,
      "forsale": true,
      "material": "enamel on plywood",
      "tags": ["paintings"]
    },
    {
      "title": "Foil Face",
      "date": "2023-01-01T00:00:00.000Z",
      "summary": "Foil Face: a painting by David Rhoden",
      "image": "/static/img/paintings/foilface.jpg",
      "height": null,
      "width": null,
      "price": null,
      "forsale": true,
      "material": "enamel on plywood",
      "tags": ["paintings"]
    },
    {
      "title": "Football",
      "date": "2021-02-24T00:00:00.000Z",
      "summary": "Football: a painting by David Rhoden",
      "image": "/static/img/paintings/football-feb-24-2021.jpg",
      "height": null,
      "width": null,
      "price": null,
      "forsale": true,
      "material": "enamel on plywood",
      "tags": ["paintings"]
    },
    {
      "title": "Fuckhead",
      "date": "2023-01-01T00:00:00.000Z",
      "summary": "Fuckhead: a painting by David Rhoden",
      "image": "/static/img/paintings/fuckhead.jpg",
      "height": null,
      "width": null,
      "price": null,
      "forsale": true,
      "material": "enamel on plywood",
      "tags": ["paintings"]
    },
    {
      "title": "Green Heads",
      "date": "2023-01-01T00:00:00.000Z",
      "summary": "Green Heads: a painting by David Rhoden",
      "image": "/static/img/paintings/greenheads.jpg",
      "height": null,
      "width": null,
      "price": null,
      "forsale": true,
      "material": "enamel on plywood",
      "tags": ["paintings"]
    },
    {
      "title": "I Don't Like This",
      "date": "2023-01-01T00:00:00.000Z",
      "summary": "I Don't Like This: a painting by David Rhoden",
      "image": "/static/img/paintings/i-dont-like-this.jpg",
      "height": null,
      "width": null,
      "price": null,
      "forsale": true,
      "material": "enamel on plywood",
      "tags": ["paintings"]
    },
    {
      "title": "I'm Over It",
      "date": "2017-12-17T00:00:00.000Z",
      "summary": "I'm Over It: a painting by David Rhoden",
      "image": "/static/img/paintings/im-over-it-dec-17-2017.jpg",
      "height": null,
      "width": null,
      "price": null,
      "forsale": true,
      "material": "enamel on plywood",
      "tags": ["paintings"]
    },
    {
      "title": "Inhaler",
      "date": "2023-01-01T00:00:00.000Z",
      "summary": "Inhaler: a painting by David Rhoden",
      "image": "/static/img/paintings/inhaler-on-paper.jpg",
      "height": null,
      "width": null,
      "price": null,
      "forsale": true,
      "material": "enamel on paper",
      "tags": ["paintings"]
    },
    {
      "title": "K-Doe",
      "date": "2023-01-01T00:00:00.000Z",
      "summary": "K-Doe: a painting by David Rhoden",
      "image": "/static/img/paintings/kdoe-on-cardboard.jpg",
      "height": null,
      "width": null,
      "price": null,
      "forsale": true,
      "material": "enamel on cardboard",
      "tags": ["paintings"]
    },
    {
      "title": "Knife Guy",
      "date": "2013-01-01T00:00:00.000Z",
      "summary": "Knife Guy: a painting by David Rhoden",
      "image": "/static/img/paintings/knife-guy-2013.jpg",
      "height": null,
      "width": null,
      "price": null,
      "forsale": true,
      "material": "enamel on plywood",
      "tags": ["paintings"]
    },
    {
      "title": "Le Pétomane",
      "date": "2023-01-01T00:00:00.000Z",
      "summary": "Le Pétomane: a painting by David Rhoden",
      "image": "/static/img/paintings/le-petomane-painting.jpg",
      "height": null,
      "width": null,
      "price": null,
      "forsale": true,
      "material": "enamel on plywood",
      "tags": ["paintings"]
    },
    {
      "title": "Little People",
      "date": "2023-01-01T00:00:00.000Z",
      "summary": "Little People: a painting by David Rhoden",
      "image": "/static/img/paintings/little-people.jpg",
      "height": null,
      "width": null,
      "price": null,
      "forsale": true,
      "material": "enamel on plywood",
      "tags": ["paintings"]
    },
    {
      "title": "Long Legs",
      "date": "2020-01-01T00:00:00.000Z",
      "summary": "Long Legs: a painting by David Rhoden",
      "image": "/static/img/paintings/long-legs-jan-1-2020.jpg",
      "height": null,
      "width": null,
      "price": null,
      "forsale": true,
      "material": "enamel on plywood",
      "tags": ["paintings"]
    },
    {
      "title": "Many-Eyed Monster 1",
      "date": "2023-01-01T00:00:00.000Z",
      "summary": "Many-Eyed Monster 1: a painting by David Rhoden",
      "image": "/static/img/paintings/many-eyed-monster-1.jpg",
      "height": null,
      "width": null,
      "price": null,
      "forsale": true,
      "material": "enamel on plywood",
      "tags": ["paintings"]
    },
    {
      "title": "Negatory",
      "date": "2017-12-01T00:00:00.000Z",
      "summary": "Negatory: a painting by David Rhoden",
      "image": "/static/img/paintings/negatory-completed-dec-1-2017.jpg",
      "height": null,
      "width": null,
      "price": null,
      "forsale": true,
      "material": "enamel on plywood",
      "tags": ["paintings"]
    },
    {
      "title": "New Guy at the Office",
      "date": "2023-01-01T00:00:00.000Z",
      "summary": "New Guy at the Office: a painting by David Rhoden",
      "image": "/static/img/paintings/newguyattheoffice.jpg",
      "height": null,
      "width": null,
      "price": null,
      "forsale": true,
      "material": "enamel on plywood",
      "tags": ["paintings"]
    },
    {
      "title": "No No No No No",
      "date": "2023-01-01T00:00:00.000Z",
      "summary": "No No No No No: a painting by David Rhoden",
      "image": "/static/img/paintings/nonononono.jpg",
      "height": null,
      "width": null,
      "price": null,
      "forsale": true,
      "material": "enamel on plywood",
      "tags": ["paintings"]
    },
    {
      "title": "Nope Never Ha Ha No",
      "date": "2023-01-01T00:00:00.000Z",
      "summary": "Nope Never Ha Ha No: a painting by David Rhoden",
      "image": "/static/img/paintings/nope-never-ha-ha-no.jpg",
      "height": null,
      "width": null,
      "price": null,
      "forsale": true,
      "material": "enamel on plywood",
      "tags": ["paintings"]
    },
    {
      "title": "Oh No Never",
      "date": "2023-01-01T00:00:00.000Z",
      "summary": "Oh No Never: a painting by David Rhoden",
      "image": "/static/img/paintings/ohnonever.jpg",
      "height": null,
      "width": null,
      "price": null,
      "forsale": true,
      "material": "enamel on plywood",
      "tags": ["paintings"]
    },
    {
      "title": "One Arm",
      "date": "2023-01-01T00:00:00.000Z",
      "summary": "One Arm: a painting by David Rhoden",
      "image": "/static/img/paintings/one-arm-at-gogos.jpg",
      "height": null,
      "width": null,
      "price": null,
      "forsale": true,
      "material": "enamel on plywood",
      "tags": ["paintings"]
    },
    {
      "title": "Organic Form (Blue)",
      "date": "2023-01-01T00:00:00.000Z",
      "summary": "Organic Form (Blue): a painting by David Rhoden",
      "image": "/static/img/paintings/organic-form-1-blue.jpg",
      "height": null,
      "width": null,
      "price": null,
      "forsale": true,
      "material": "enamel on plywood",
      "tags": ["paintings", "organic form"]
    },
    {
      "title": "Pink Lucha",
      "date": "2025-06-28T00:00:00.000Z",
      "summary": "Pink Lucha: a painting by David Rhoden",
      "image": "/static/img/paintings/pink-lucha-post-wash-jun-28-2025.jpeg",
      "height": null,
      "width": null,
      "price": null,
      "forsale": true,
      "material": "enamel on plywood",
      "tags": ["paintings"]
    },
    {
      "title": "Pink Luchador",
      "date": "2023-01-01T00:00:00.000Z",
      "summary": "Pink Luchador: a painting by David Rhoden",
      "image": "/static/img/paintings/pinkluchadorwithshadow.jpg",
      "height": null,
      "width": null,
      "price": null,
      "forsale": true,
      "material": "enamel on plywood",
      "tags": ["paintings"]
    },
    {
      "title": "Pink Squiggle",
      "date": "2015-05-02T00:00:00.000Z",
      "summary": "Pink Squiggle: a painting by David Rhoden",
      "image": "/static/img/paintings/squiggle-pink-may-2-2015.jpg",
      "height": null,
      "width": null,
      "price": null,
      "forsale": true,
      "material": "enamel on plywood",
      "tags": ["paintings", "squiggles"]
    },
    {
      "title": "Posing Woman",
      "date": "2023-01-01T00:00:00.000Z",
      "summary": "Posing Woman: a painting by David Rhoden",
      "image": "/static/img/paintings/posingwoman.jpg",
      "height": null,
      "width": null,
      "price": null,
      "forsale": true,
      "material": "enamel on plywood",
      "tags": ["paintings"]
    },
    {
      "title": "Screaming Guy",
      "date": "2023-01-01T00:00:00.000Z",
      "summary": "Screaming Guy: a painting by David Rhoden",
      "image": "/static/img/paintings/screaming-guy.jpg",
      "height": null,
      "width": null,
      "price": null,
      "forsale": true,
      "material": "enamel on plywood",
      "tags": ["paintings"]
    },
    {
      "title": "Seriously",
      "date": "2020-12-29T00:00:00.000Z",
      "summary": "Seriously: a painting by David Rhoden",
      "image": "/static/img/paintings/seriously-dec-29-2020.jpg",
      "height": null,
      "width": null,
      "price": null,
      "forsale": true,
      "material": "enamel on plywood",
      "tags": ["paintings"]
    },
    {
      "title": "Small Blue Suit",
      "date": "2023-01-01T00:00:00.000Z",
      "summary": "Small Blue Suit: a painting by David Rhoden",
      "image": "/static/img/paintings/smallbluesuit2.jpg",
      "height": null,
      "width": null,
      "price": null,
      "forsale": true,
      "material": "enamel on plywood",
      "tags": ["paintings"]
    },
    {
      "title": "Smoker",
      "date": "2023-01-01T00:00:00.000Z",
      "summary": "Smoker: a painting by David Rhoden",
      "image": "/static/img/paintings/smoker.jpeg",
      "height": null,
      "width": null,
      "price": null,
      "forsale": true,
      "material": "enamel on plywood",
      "tags": ["paintings"]
    },
    {
      "title": "Sneak",
      "date": "2023-01-01T00:00:00.000Z",
      "summary": "Sneak: a painting by David Rhoden",
      "image": "/static/img/paintings/sneak.jpg",
      "height": null,
      "width": null,
      "price": null,
      "forsale": true,
      "material": "enamel on plywood",
      "tags": ["paintings"]
    },
    {
      "title": "Standing Man",
      "date": "2023-01-01T00:00:00.000Z",
      "summary": "Standing Man: a painting by David Rhoden",
      "image": "/static/img/paintings/standingman.jpg",
      "height": null,
      "width": null,
      "price": null,
      "forsale": true,
      "material": "enamel on plywood",
      "tags": ["paintings"]
    },
    {
      "title": "Two Heads",
      "date": "2023-01-01T00:00:00.000Z",
      "summary": "Two Heads: a painting by David Rhoden",
      "image": "/static/img/paintings/paintingtwoheads.jpg",
      "height": null,
      "width": null,
      "price": null,
      "forsale": true,
      "material": "enamel on plywood",
      "tags": ["paintings"]
    },
    {
      "title": "Two Human Figures",
      "date": "2023-01-01T00:00:00.000Z",
      "summary": "Two Human Figures: a painting by David Rhoden",
      "image": "/static/img/paintings/twohumanfigures.jpg",
      "height": null,
      "width": null,
      "price": null,
      "forsale": true,
      "material": "enamel on plywood",
      "tags": ["paintings"]
    },
    {
      "title": "Two Mouth Creature",
      "date": "2012-08-22T00:00:00.000Z",
      "summary": "Two Mouth Creature: a painting by David Rhoden",
      "image": "/static/img/paintings/two-mouth-creature-aug-22-2012.jpg",
      "height": null,
      "width": null,
      "price": null,
      "forsale": true,
      "material": "enamel on plywood",
      "tags": ["paintings"]
    },
    {
      "title": "Typical Man",
      "date": "2022-08-29T00:00:00.000Z",
      "summary": "Typical Man: a painting by David Rhoden",
      "image": "/static/img/paintings/typical-man-new-painting-aug-29-2022.jpg",
      "height": null,
      "width": null,
      "price": null,
      "forsale": true,
      "material": "enamel on plywood",
      "tags": ["paintings"]
    },
    {
      "title": "Unimog",
      "date": "2022-02-20T00:00:00.000Z",
      "summary": "Unimog: a painting by David Rhoden",
      "image": "/static/img/paintings/unimog-feb-20-2022.jpg",
      "height": null,
      "width": null,
      "price": null,
      "forsale": true,
      "material": "enamel on plywood",
      "tags": ["paintings"]
    },
    {
      "title": "Unreal",
      "date": "2023-01-01T00:00:00.000Z",
      "summary": "Unreal: a painting by David Rhoden",
      "image": "/static/img/paintings/unreal-lost-painting.jpg",
      "height": null,
      "width": null,
      "price": "LOST",
      "forsale": false,
      "material": "enamel on plywood",
      "tags": ["paintings"]
    },
    {
      "title": "Urinator",
      "date": "2023-01-01T00:00:00.000Z",
      "summary": "Urinator: a painting by David Rhoden",
      "image": "/static/img/paintings/urinator.jpg",
      "height": null,
      "width": null,
      "price": null,
      "forsale": true,
      "material": "enamel on plywood",
      "tags": ["paintings"]
    },
    {
      "title": "Yellow Fellow",
      "date": "2023-01-01T00:00:00.000Z",
      "summary": "Yellow Fellow: a painting by David Rhoden",
      "image": "/static/img/paintings/yellowfellow.jpg",
      "height": null,
      "width": null,
      "price": null,
      "forsale": true,
      "material": "enamel on plywood",
      "tags": ["paintings"]
    },
    {
      "title": "Yellow Silver Head",
      "date": "2023-01-01T00:00:00.000Z",
      "summary": "Yellow Silver Head: a painting by David Rhoden",
      "image": "/static/img/paintings/yellowsilverhead.jpg",
      "height": null,
      "width": null,
      "price": null,
      "forsale": true,
      "material": "enamel on plywood",
      "tags": ["paintings"]
    },
    {
      "title": "Yellow Squiggle",
      "date": "2016-08-07T00:00:00.000Z",
      "summary": "Yellow Squiggle: a painting by David Rhoden",
      "image": "/static/img/paintings/squiggle-yellow-aug-7-2016.jpg",
      "height": null,
      "width": null,
      "price": null,
      "forsale": true,
      "material": "enamel on plywood",
      "tags": ["paintings", "squiggles"]
    }
  ]
}